{"trainNumber":"01456","trainName":"MAU PUNE SPECIAL","stationFrom":"MAU","stationTo":"PUNE JN","trainRunsOnMon":"N","trainRunsOnTue":"N","trainRunsOnWed":"N","trainRunsOnThu":"N","trainRunsOnFri":"Y","trainRunsOnSat":"N","trainRunsOnSun":"N","timeStamp":"Feb 3, 2025 10:44:41 AM","stationList":[{"stationCode":"MAU","stationName":"MAU JN","arrivalTime":"00:00","departureTime":"23:50","routeNumber":"0","haltTime":"--","distance":"0.0","dayCount":"1","stnSerialNumber":"1"},{"stationCode":"AMH","stationName":"AZAMGARH","arrivalTime":"00:45","departureTime":"00:50","routeNumber":"0","haltTime":"05:00","distance":"43.04","dayCount":"2","stnSerialNumber":"2"},{"stationCode":"SHG","stationName":"SHAHGANJ JN","arrivalTime":"02:00","departureTime":"02:10","routeNumber":"0","haltTime":"10:00","distance":"99.75","dayCount":"2","stnSerialNumber":"3"},{"stationCode":"BSB","stationName":"VARANASI JN","arrivalTime":"05:25","departureTime":"05:35","routeNumber":"0","haltTime":"10:00","distance":"190.56","dayCount":"2","stnSerialNumber":"4"},{"stationCode":"CAR","stationName":"CHUNAR","arrivalTime":"07:00","departureTime":"07:02","routeNumber":"0","haltTime":"02:00","distance":"235.11","dayCount":"2","stnSerialNumber":"5"},{"stationCode":"MZP","stationName":"MIRZAPUR","arrivalTime":"07:30","departureTime":"07:32","routeNumber":"0","haltTime":"02:00","distance":"266.19","dayCount":"2","stnSerialNumber":"6"},{"stationCode":"PCOI","stationName":"PRAYAGRAJCHEOKI","arrivalTime":"09:10","departureTime":"09:20","routeNumber":"0","haltTime":"10:00","distance":"346.99","dayCount":"2","stnSerialNumber":"7"},{"stationCode":"MKP","stationName":"MANIKPUR","arrivalTime":"12:18","departureTime":"12:20","routeNumber":"0","haltTime":"02:00","distance":"438.92","dayCount":"2","stnSerialNumber":"8"},{"stationCode":"STA","stationName":"SATNA","arrivalTime":"13:50","departureTime":"13:55","routeNumber":"0","haltTime":"05:00","distance":"516.37","dayCount":"2","stnSerialNumber":"9"},{"stationCode":"MYR","stationName":"MAIHAR","arrivalTime":"14:23","departureTime":"14:25","routeNumber":"0","haltTime":"02:00","distance":"551.65","dayCount":"2","stnSerialNumber":"10"},{"stationCode":"KTE","stationName":"KATNI","arrivalTime":"15:05","departureTime":"15:10","routeNumber":"0","haltTime":"05:00","distance":"614.57","dayCount":"2","stnSerialNumber":"11"},{"stationCode":"JBP","stationName":"JABALPUR","arrivalTime":"17:00","departureTime":"17:10","routeNumber":"0","haltTime":"10:00","distance":"705.36","dayCount":"2","stnSerialNumber":"12"},{"stationCode":"NU","stationName":"NARSINGHPUR","arrivalTime":"18:18","departureTime":"18:20","routeNumber":"0","haltTime":"02:00","distance":"789.39","dayCount":"2","stnSerialNumber":"13"},{"stationCode":"PPI","stationName":"PIPARIYA","arrivalTime":"19:23","departureTime":"19:25","routeNumber":"0","haltTime":"02:00","distance":"883.18","dayCount":"2","stnSerialNumber":"14"},{"stationCode":"ET","stationName":"ITARSI JN","arrivalTime":"22:30","departureTime":"22:40","routeNumber":"0","haltTime":"10:00","distance":"950.51","dayCount":"2","stnSerialNumber":"15"},{"stationCode":"BPF","stationName":"BANAPURA","arrivalTime":"23:06","departureTime":"23:08","routeNumber":"0","haltTime":"02:00","distance":"983.84","dayCount":"2","stnSerialNumber":"16"},{"stationCode":"HD","stationName":"HARDA","arrivalTime":"23:38","departureTime":"23:40","routeNumber":"0","haltTime":"02:00","distance":"1026.08","dayCount":"2","stnSerialNumber":"17"},{"stationCode":"KKN","stationName":"KHIRKIYA","arrivalTime":"00:05","departureTime":"00:07","routeNumber":"0","haltTime":"02:00","distance":"1057.82","dayCount":"3","stnSerialNumber":"18"},{"stationCode":"CAER","stationName":"CHHANERA","arrivalTime":"00:45","departureTime":"00:47","routeNumber":"0","haltTime":"02:00","distance":"1088.63","dayCount":"3","stnSerialNumber":"19"},{"stationCode":"TLV","stationName":"TALVADYA","arrivalTime":"01:10","departureTime":"01:12","routeNumber":"0","haltTime":"02:00","distance":"1118.3","dayCount":"3","stnSerialNumber":"20"},{"stationCode":"KNW","stationName":"KHANDWA","arrivalTime":"01:55","departureTime":"02:00","routeNumber":"0","haltTime":"05:00","distance":"1133.96","dayCount":"3","stnSerialNumber":"21"},{"stationCode":"BSL","stationName":"BHUSAVAL JN","arrivalTime":"04:50","departureTime":"04:53","routeNumber":"0","haltTime":"03:00","distance":"1257.43","dayCount":"3","stnSerialNumber":"22"},{"stationCode":"JL","stationName":"JALGAON JN","arrivalTime":"05:15","departureTime":"05:17","routeNumber":"0","haltTime":"02:00","distance":"1281.56","dayCount":"3","stnSerialNumber":"23"},{"stationCode":"MMR","stationName":"MANMAD JN","arrivalTime":"08:25","departureTime":"08:30","routeNumber":"0","haltTime":"05:00","distance":"1441.37","dayCount":"3","stnSerialNumber":"24"},{"stationCode":"ANK","stationName":"ANKAI","arrivalTime":"08:54","departureTime":"08:55","routeNumber":"0","haltTime":"01:00","distance":"1454.58","dayCount":"3","stnSerialNumber":"25"},{"stationCode":"BAP","stationName":"BELAPUR","arrivalTime":"10:20","departureTime":"10:22","routeNumber":"0","haltTime":"02:00","distance":"1527.24","dayCount":"3","stnSerialNumber":"26"},{"stationCode":"ANG","stationName":"AHMADNAGAR","arrivalTime":"11:28","departureTime":"11:30","routeNumber":"0","haltTime":"02:00","distance":"1594.15","dayCount":"3","stnSerialNumber":"27"},{"stationCode":"DDCC","stationName":"DAUND CHORD LIN","arrivalTime":"14:28","departureTime":"14:30","routeNumber":"0","haltTime":"02:00","distance":"1675.72","dayCount":"3","stnSerialNumber":"28"},{"stationCode":"PUNE","stationName":"PUNE JN","arrivalTime":"15:45","departureTime":"00:00","routeNumber":"0","haltTime":"--","distance":"1748.53","dayCount":"3","stnSerialNumber":"29"}],"generatedTimeStamp":{"year":2025,"month":2,"day":3,"hour":10,"minute":44,"second":41}}
