{"trainNumber":"02421","trainName":"SFG DLI SUP SPL","stationFrom":"SFG","stationTo":"DELHI","trainRunsOnMon":"N","trainRunsOnTue":"N","trainRunsOnWed":"N","trainRunsOnThu":"N","trainRunsOnFri":"N","trainRunsOnSat":"N","trainRunsOnSun":"Y","timeStamp":"Feb 10, 2025 10:38:29 AM","stationList":[{"stationCode":"SFG","stationName":"SUBEDARGANJ","arrivalTime":"00:00","departureTime":"21:35","routeNumber":"0","haltTime":"--","distance":"0.0","dayCount":"1","stnSerialNumber":"1"},{"stationCode":"FTP","stationName":"FATEHPUR","arrivalTime":"22:45","departureTime":"22:47","routeNumber":"0","haltTime":"02:00","distance":"112.91","dayCount":"1","stnSerialNumber":"2"},{"stationCode":"GOY","stationName":"GOVINDPURI","arrivalTime":"00:15","departureTime":"00:20","routeNumber":"0","haltTime":"05:00","distance":"192.51","dayCount":"2","stnSerialNumber":"3"},{"stationCode":"ETW","stationName":"ETAWAH JN","arrivalTime":"02:00","departureTime":"02:02","routeNumber":"0","haltTime":"02:00","distance":"328.08","dayCount":"2","stnSerialNumber":"4"},{"stationCode":"TDL","stationName":"TUNDLA JN","arrivalTime":"03:33","departureTime":"03:35","routeNumber":"0","haltTime":"02:00","distance":"419.94","dayCount":"2","stnSerialNumber":"5"},{"stationCode":"ALJN","stationName":"ALIGARH JN","arrivalTime":"04:45","departureTime":"04:47","routeNumber":"0","haltTime":"02:00","distance":"497.95","dayCount":"2","stnSerialNumber":"6"},{"stationCode":"DLI","stationName":"DELHI","arrivalTime":"08:55","departureTime":"00:00","routeNumber":"0","haltTime":"--","distance":"623.66","dayCount":"2","stnSerialNumber":"7"}],"generatedTimeStamp":{"year":2025,"month":2,"day":10,"hour":10,"minute":38,"second":29}}
