{"trainNumber":"12536","trainName":"LJN GARIBRATH","stationFrom":"R","stationTo":"LUCKNOW NE","trainRunsOnMon":"N","trainRunsOnTue":"Y","trainRunsOnWed":"N","trainRunsOnThu":"N","trainRunsOnFri":"Y","trainRunsOnSat":"N","trainRunsOnSun":"N","timeStamp":"Feb 3, 2025 11:02:42 AM","stationList":[{"stationCode":"R","stationName":"RAIPUR JN","arrivalTime":"00:00","departureTime":"12:05","routeNumber":"0","haltTime":"--","distance":"0.0","dayCount":"1","stnSerialNumber":"1"},{"stationCode":"BYT","stationName":"BHATAPARA","arrivalTime":"12:53","departureTime":"12:55","routeNumber":"0","haltTime":"02:00","distance":"64.0","dayCount":"1","stnSerialNumber":"2"},{"stationCode":"USL","stationName":"USLAPUR","arrivalTime":"14:05","departureTime":"14:15","routeNumber":"0","haltTime":"10:00","distance":"115.67","dayCount":"1","stnSerialNumber":"3"},{"stationCode":"PND","stationName":"PENDRA ROAD","arrivalTime":"15:41","departureTime":"15:43","routeNumber":"0","haltTime":"02:00","distance":"210.37","dayCount":"1","stnSerialNumber":"4"},{"stationCode":"APR","stationName":"ANUPPUR JN","arrivalTime":"16:21","departureTime":"16:26","routeNumber":"0","haltTime":"05:00","distance":"260.51","dayCount":"1","stnSerialNumber":"5"},{"stationCode":"SDL","stationName":"SHAHDOL","arrivalTime":"17:08","departureTime":"17:10","routeNumber":"0","haltTime":"02:00","distance":"301.51","dayCount":"1","stnSerialNumber":"6"},{"stationCode":"KTE","stationName":"KATNI","arrivalTime":"19:40","departureTime":"19:45","routeNumber":"0","haltTime":"05:00","distance":"428.29","dayCount":"1","stnSerialNumber":"7"},{"stationCode":"MYR","stationName":"MAIHAR","arrivalTime":"19:47","departureTime":"19:48","routeNumber":"0","haltTime":"01:00","distance":"491.21","dayCount":"1","stnSerialNumber":"8"},{"stationCode":"STA","stationName":"SATNA","arrivalTime":"20:55","departureTime":"21:00","routeNumber":"0","haltTime":"05:00","distance":"526.49","dayCount":"1","stnSerialNumber":"9"},{"stationCode":"MKP","stationName":"MANIKPUR","arrivalTime":"21:02","departureTime":"21:03","routeNumber":"0","haltTime":"01:00","distance":"603.94","dayCount":"1","stnSerialNumber":"10"},{"stationCode":"CKTD","stationName":"CHITRAKUTDHAM K","arrivalTime":"23:11","departureTime":"23:13","routeNumber":"0","haltTime":"02:00","distance":"635.06","dayCount":"1","stnSerialNumber":"11"},{"stationCode":"ATE","stationName":"ATARRA","arrivalTime":"23:38","departureTime":"23:40","routeNumber":"0","haltTime":"02:00","distance":"672.07","dayCount":"1","stnSerialNumber":"12"},{"stationCode":"BNDA","stationName":"BANDA JN","arrivalTime":"00:20","departureTime":"00:25","routeNumber":"0","haltTime":"05:00","distance":"704.02","dayCount":"2","stnSerialNumber":"13"},{"stationCode":"RGU","stationName":"RAGAUL","arrivalTime":"00:56","departureTime":"00:58","routeNumber":"0","haltTime":"02:00","distance":"744.38","dayCount":"2","stnSerialNumber":"14"},{"stationCode":"CNB","stationName":"KANPUR CENTRAL","arrivalTime":"03:20","departureTime":"03:25","routeNumber":"0","haltTime":"05:00","distance":"848.52","dayCount":"2","stnSerialNumber":"15"},{"stationCode":"LJN","stationName":"LUCKNOW NE","arrivalTime":"05:10","departureTime":"00:00","routeNumber":"0","haltTime":"--","distance":"922.23","dayCount":"2","stnSerialNumber":"16"}],"generatedTimeStamp":{"year":2025,"month":2,"day":3,"hour":11,"minute":2,"second":42}}
