{"trainNumber":"13046","trainName":"MAYURAKSHI EXP","stationFrom":"DGHR","stationTo":"HOWRAH JN","trainRunsOnMon":"Y","trainRunsOnTue":"Y","trainRunsOnWed":"Y","trainRunsOnThu":"Y","trainRunsOnFri":"Y","trainRunsOnSat":"Y","trainRunsOnSun":"Y","timeStamp":"Feb 4, 2025 7:19:49 PM","stationList":[{"stationCode":"DGHR","stationName":"DEOGHAR","arrivalTime":"00:00","departureTime":"03:15","routeNumber":"0","haltTime":"--","distance":"0.0","dayCount":"1","stnSerialNumber":"1"},{"stationCode":"GRMA","stationName":"GHORMARA","arrivalTime":"03:29","departureTime":"03:30","routeNumber":"0","haltTime":"01:00","distance":"19.68","dayCount":"1","stnSerialNumber":"2"},{"stationCode":"BSKH","stationName":"BASUKINATH","arrivalTime":"03:46","departureTime":"03:47","routeNumber":"0","haltTime":"01:00","distance":"42.52","dayCount":"1","stnSerialNumber":"3"},{"stationCode":"DUMK","stationName":"DUMKA","arrivalTime":"04:04","departureTime":"04:06","routeNumber":"0","haltTime":"02:00","distance":"65.13","dayCount":"1","stnSerialNumber":"4"},{"stationCode":"SKIP","stationName":"SIKARIPARA","arrivalTime":"04:26","departureTime":"04:27","routeNumber":"0","haltTime":"01:00","distance":"89.64","dayCount":"1","stnSerialNumber":"5"},{"stationCode":"PRGR","stationName":"PINARGARIA","arrivalTime":"04:44","departureTime":"04:45","routeNumber":"0","haltTime":"01:00","distance":"110.74","dayCount":"1","stnSerialNumber":"6"},{"stationCode":"RPH","stationName":"RAMPUR HAT","arrivalTime":"05:15","departureTime":"05:20","routeNumber":"0","haltTime":"05:00","distance":"129.71","dayCount":"1","stnSerialNumber":"7"},{"stationCode":"MLV","stationName":"MALLARPUR","arrivalTime":"05:34","departureTime":"05:35","routeNumber":"0","haltTime":"01:00","distance":"142.23","dayCount":"1","stnSerialNumber":"8"},{"stationCode":"GHLE","stationName":"GADADHARPUR","arrivalTime":"05:43","departureTime":"05:44","routeNumber":"0","haltTime":"01:00","distance":"150.33","dayCount":"1","stnSerialNumber":"9"},{"stationCode":"SNT","stationName":"SAINTHIA","arrivalTime":"05:52","departureTime":"05:54","routeNumber":"0","haltTime":"02:00","distance":"157.52","dayCount":"1","stnSerialNumber":"10"},{"stationCode":"SURI","stationName":"SIURI","arrivalTime":"06:13","departureTime":"06:15","routeNumber":"0","haltTime":"02:00","distance":"176.78","dayCount":"1","stnSerialNumber":"11"},{"stationCode":"KOX","stationName":"KACHUJOR","arrivalTime":"06:24","departureTime":"06:25","routeNumber":"0","haltTime":"01:00","distance":"185.64","dayCount":"1","stnSerialNumber":"12"},{"stationCode":"CPLE","stationName":"CHINPAI","arrivalTime":"06:32","departureTime":"06:33","routeNumber":"0","haltTime":"01:00","distance":"189.13","dayCount":"1","stnSerialNumber":"13"},{"stationCode":"DUJ","stationName":"DUBRAJPUR","arrivalTime":"06:40","departureTime":"06:41","routeNumber":"0","haltTime":"01:00","distance":"195.44","dayCount":"1","stnSerialNumber":"14"},{"stationCode":"PCR","stationName":"PANCHRA","arrivalTime":"06:48","departureTime":"06:49","routeNumber":"0","haltTime":"01:00","distance":"201.68","dayCount":"1","stnSerialNumber":"15"},{"stationCode":"BMGA","stationName":"BHIMGARA","arrivalTime":"06:56","departureTime":"06:57","routeNumber":"0","haltTime":"01:00","distance":"207.4","dayCount":"1","stnSerialNumber":"16"},{"stationCode":"PAW","stationName":"PANDABESWAR","arrivalTime":"07:03","departureTime":"07:04","routeNumber":"0","haltTime":"01:00","distance":"210.58","dayCount":"1","stnSerialNumber":"17"},{"stationCode":"UKA","stationName":"UKHRA","arrivalTime":"07:14","departureTime":"07:15","routeNumber":"0","haltTime":"01:00","distance":"218.91","dayCount":"1","stnSerialNumber":"18"},{"stationCode":"KJME","stationName":"KAJORAGRAM","arrivalTime":"07:23","departureTime":"07:24","routeNumber":"0","haltTime":"01:00","distance":"225.61","dayCount":"1","stnSerialNumber":"19"},{"stationCode":"UDL","stationName":"ANDAL JN","arrivalTime":"07:40","departureTime":"07:42","routeNumber":"0","haltTime":"02:00","distance":"230.92","dayCount":"1","stnSerialNumber":"20"},{"stationCode":"OYR","stationName":"WARIA","arrivalTime":"07:50","departureTime":"07:52","routeNumber":"0","haltTime":"02:00","distance":"238.39","dayCount":"1","stnSerialNumber":"21"},{"stationCode":"DGR","stationName":"DURGAPUR","arrivalTime":"08:00","departureTime":"08:02","routeNumber":"0","haltTime":"02:00","distance":"247.28","dayCount":"1","stnSerialNumber":"22"},{"stationCode":"PAN","stationName":"PANAGARH","arrivalTime":"08:15","departureTime":"08:16","routeNumber":"0","haltTime":"01:00","distance":"262.63","dayCount":"1","stnSerialNumber":"23"},{"stationCode":"MNAE","stationName":"MANKAR","arrivalTime":"08:27","departureTime":"08:28","routeNumber":"0","haltTime":"01:00","distance":"273.09","dayCount":"1","stnSerialNumber":"24"},{"stationCode":"BWN","stationName":"BARDDHAMAN JN","arrivalTime":"09:16","departureTime":"09:18","routeNumber":"0","haltTime":"02:00","distance":"310.6","dayCount":"1","stnSerialNumber":"25"},{"stationCode":"BDC","stationName":"BANDEL JN","arrivalTime":"10:23","departureTime":"10:25","routeNumber":"0","haltTime":"02:00","distance":"378.04","dayCount":"1","stnSerialNumber":"26"},{"stationCode":"HWH","stationName":"HOWRAH JN","arrivalTime":"11:35","departureTime":"00:00","routeNumber":"0","haltTime":"--","distance":"417.33","dayCount":"1","stnSerialNumber":"27"}],"generatedTimeStamp":{"year":2025,"month":2,"day":4,"hour":19,"minute":19,"second":49}}
