{"trainNumber":"15103","trainName":"BSBS INTERCITY","stationFrom":"GKP","stationTo":"BANARAS","trainRunsOnMon":"Y","trainRunsOnTue":"Y","trainRunsOnWed":"Y","trainRunsOnThu":"Y","trainRunsOnFri":"Y","trainRunsOnSat":"Y","trainRunsOnSun":"Y","timeStamp":"Feb 4, 2025 7:23:48 PM","stationList":[{"stationCode":"GKP","stationName":"GORAKHPUR JN","arrivalTime":"00:00","departureTime":"16:15","routeNumber":"0","haltTime":"--","distance":"0.0","dayCount":"1","stnSerialNumber":"1"},{"stationCode":"GKC","stationName":"GORAKHPUR CANT","arrivalTime":"16:17","departureTime":"16:18","routeNumber":"0","haltTime":"01:00","distance":"3.22","dayCount":"1","stnSerialNumber":"2"},{"stationCode":"GB","stationName":"GAURI BAZAR","arrivalTime":"16:20","departureTime":"16:21","routeNumber":"0","haltTime":"01:00","distance":"34.2","dayCount":"1","stnSerialNumber":"3"},{"stationCode":"DEOS","stationName":"DEORIA SADAR","arrivalTime":"17:13","departureTime":"17:18","routeNumber":"0","haltTime":"05:00","distance":"49.49","dayCount":"1","stnSerialNumber":"4"},{"stationCode":"BTT","stationName":"BHATNI JN","arrivalTime":"17:41","departureTime":"17:43","routeNumber":"0","haltTime":"02:00","distance":"70.4","dayCount":"1","stnSerialNumber":"5"},{"stationCode":"SRU","stationName":"SALEMPUR JN","arrivalTime":"18:02","departureTime":"18:04","routeNumber":"0","haltTime":"02:00","distance":"80.69","dayCount":"1","stnSerialNumber":"6"},{"stationCode":"LRD","stationName":"LAR ROAD","arrivalTime":"18:18","departureTime":"18:20","routeNumber":"0","haltTime":"02:00","distance":"90.18","dayCount":"1","stnSerialNumber":"7"},{"stationCode":"BLTR","stationName":"BELTHARA ROAD","arrivalTime":"18:33","departureTime":"18:35","routeNumber":"0","haltTime":"02:00","distance":"103.18","dayCount":"1","stnSerialNumber":"8"},{"stationCode":"KER","stationName":"KIRIHRAPUR","arrivalTime":"18:48","departureTime":"18:50","routeNumber":"0","haltTime":"02:00","distance":"117.03","dayCount":"1","stnSerialNumber":"9"},{"stationCode":"IAA","stationName":"INDARA JN","arrivalTime":"19:02","departureTime":"19:04","routeNumber":"0","haltTime":"02:00","distance":"130.31","dayCount":"1","stnSerialNumber":"10"},{"stationCode":"MAU","stationName":"MAU JN","arrivalTime":"19:15","departureTime":"19:20","routeNumber":"0","haltTime":"05:00","distance":"138.31","dayCount":"1","stnSerialNumber":"11"},{"stationCode":"DLR","stationName":"DULLAHAPUR","arrivalTime":"19:44","departureTime":"19:46","routeNumber":"0","haltTime":"02:00","distance":"159.23","dayCount":"1","stnSerialNumber":"12"},{"stationCode":"JKN","stationName":"JAKHANIAN","arrivalTime":"19:56","departureTime":"19:58","routeNumber":"0","haltTime":"02:00","distance":"167.68","dayCount":"1","stnSerialNumber":"13"},{"stationCode":"SDT","stationName":"SADAT","arrivalTime":"20:10","departureTime":"20:11","routeNumber":"0","haltTime":"01:00","distance":"177.49","dayCount":"1","stnSerialNumber":"14"},{"stationCode":"MHO","stationName":"MAHPUR","arrivalTime":"20:13","departureTime":"20:14","routeNumber":"0","haltTime":"01:00","distance":"187.15","dayCount":"1","stnSerialNumber":"15"},{"stationCode":"ARJ","stationName":"AUNRIHAR JN","arrivalTime":"20:31","departureTime":"20:33","routeNumber":"0","haltTime":"02:00","distance":"196.0","dayCount":"1","stnSerialNumber":"16"},{"stationCode":"RJI","stationName":"RAJAWARI","arrivalTime":"20:35","departureTime":"20:36","routeNumber":"0","haltTime":"01:00","distance":"204.45","dayCount":"1","stnSerialNumber":"17"},{"stationCode":"KDQ","stationName":"KADIPUR","arrivalTime":"20:38","departureTime":"20:39","routeNumber":"0","haltTime":"01:00","distance":"210.48","dayCount":"1","stnSerialNumber":"18"},{"stationCode":"SRNT","stationName":"SARNATH","arrivalTime":"20:41","departureTime":"20:42","routeNumber":"0","haltTime":"01:00","distance":"220.56","dayCount":"1","stnSerialNumber":"19"},{"stationCode":"BCY","stationName":"VARANASI CITY","arrivalTime":"21:16","departureTime":"21:18","routeNumber":"0","haltTime":"02:00","distance":"227.2","dayCount":"1","stnSerialNumber":"20"},{"stationCode":"BSB","stationName":"VARANASI JN","arrivalTime":"21:35","departureTime":"21:40","routeNumber":"0","haltTime":"05:00","distance":"231.0","dayCount":"1","stnSerialNumber":"21"},{"stationCode":"BSBS","stationName":"BANARAS","arrivalTime":"22:00","departureTime":"00:00","routeNumber":"0","haltTime":"--","distance":"234.59","dayCount":"1","stnSerialNumber":"22"}],"generatedTimeStamp":{"year":2025,"month":2,"day":4,"hour":19,"minute":23,"second":48}}
