{"trainNumber":"20607","trainName":"MYS VANDEBHARAT","stationFrom":"MAS","stationTo":"MYSURU JN","trainRunsOnMon":"Y","trainRunsOnTue":"Y","trainRunsOnWed":"N","trainRunsOnThu":"Y","trainRunsOnFri":"Y","trainRunsOnSat":"Y","trainRunsOnSun":"Y","timeStamp":"Feb 4, 2025 7:34:22 PM","stationList":[{"stationCode":"MAS","stationName":"MGR CHENNAI CTL","arrivalTime":"00:00","departureTime":"05:50","routeNumber":"0","haltTime":"--","distance":"0.0","dayCount":"1","stnSerialNumber":"1"},{"stationCode":"KPD","stationName":"KATPADI JN","arrivalTime":"07:13","departureTime":"07:15","routeNumber":"0","haltTime":"02:00","distance":"129.37","dayCount":"1","stnSerialNumber":"2"},{"stationCode":"SBC","stationName":"KSR BENGALURU","arrivalTime":"10:00","departureTime":"10:05","routeNumber":"0","haltTime":"05:00","distance":"361.31","dayCount":"1","stnSerialNumber":"3"},{"stationCode":"MYS","stationName":"MYSURU JN","arrivalTime":"12:20","departureTime":"00:00","routeNumber":"0","haltTime":"--","distance":"499.56","dayCount":"1","stnSerialNumber":"4"}],"generatedTimeStamp":{"year":2025,"month":2,"day":4,"hour":19,"minute":34,"second":22}}
