{"trainNumber":"22224","trainName":"CSMT VANDEBHARAT","stationFrom":"SNSI","stationTo":"C SHIVAJI MAH T","trainRunsOnMon":"Y","trainRunsOnTue":"N","trainRunsOnWed":"Y","trainRunsOnThu":"Y","trainRunsOnFri":"Y","trainRunsOnSat":"Y","trainRunsOnSun":"Y","timeStamp":"Feb 4, 2025 7:37:26 PM","stationList":[{"stationCode":"SNSI","stationName":"SAINAGAR SHIRDI","arrivalTime":"00:00","departureTime":"17:45","routeNumber":"0","haltTime":"--","distance":"0.0","dayCount":"1","stnSerialNumber":"1"},{"stationCode":"ANK","stationName":"ANKAI","arrivalTime":"17:47","departureTime":"17:48","routeNumber":"0","haltTime":"01:00","distance":"69.38","dayCount":"1","stnSerialNumber":"2"},{"stationCode":"NK","stationName":"NASHIK ROAD","arrivalTime":"19:33","departureTime":"19:35","routeNumber":"0","haltTime":"02:00","distance":"155.69","dayCount":"1","stnSerialNumber":"3"},{"stationCode":"IGP","stationName":"IGATPURI","arrivalTime":"19:37","departureTime":"19:38","routeNumber":"0","haltTime":"01:00","distance":"206.26","dayCount":"1","stnSerialNumber":"4"},{"stationCode":"KSRA","stationName":"KASARA","arrivalTime":"19:40","departureTime":"19:41","routeNumber":"0","haltTime":"01:00","distance":"222.21","dayCount":"1","stnSerialNumber":"5"},{"stationCode":"KYN","stationName":"KALYAN JN","arrivalTime":"21:45","departureTime":"21:47","routeNumber":"0","haltTime":"02:00","distance":"289.56","dayCount":"1","stnSerialNumber":"6"},{"stationCode":"TNA","stationName":"THANE","arrivalTime":"22:06","departureTime":"22:08","routeNumber":"0","haltTime":"02:00","distance":"309.75","dayCount":"1","stnSerialNumber":"7"},{"stationCode":"DR","stationName":"DADAR","arrivalTime":"22:28","departureTime":"22:30","routeNumber":"0","haltTime":"02:00","distance":"333.92","dayCount":"1","stnSerialNumber":"8"},{"stationCode":"CSMT","stationName":"C SHIVAJI MAH T","arrivalTime":"22:50","departureTime":"00:00","routeNumber":"0","haltTime":"--","distance":"342.76","dayCount":"1","stnSerialNumber":"9"}],"generatedTimeStamp":{"year":2025,"month":2,"day":4,"hour":19,"minute":37,"second":26}}
