{"trainNumber":"59076","trainName":"NDB PASS SPL","stationFrom":"BSL","stationTo":"NANDURBAR","trainRunsOnMon":"Y","trainRunsOnTue":"Y","trainRunsOnWed":"Y","trainRunsOnThu":"Y","trainRunsOnFri":"Y","trainRunsOnSat":"Y","trainRunsOnSun":"Y","timeStamp":"Feb 3, 2025 11:42:33 AM","stationList":[{"stationCode":"BSL","stationName":"BHUSAVAL JN","arrivalTime":"00:00","departureTime":"09:00","routeNumber":"0","haltTime":"--","distance":"0.0","dayCount":"1","stnSerialNumber":"1"},{"stationCode":"JL","stationName":"JALGAON JN","arrivalTime":"09:32","departureTime":"09:35","routeNumber":"0","haltTime":"03:00","distance":"24.13","dayCount":"1","stnSerialNumber":"2"},{"stationCode":"PLD","stationName":"PALDHI","arrivalTime":"09:55","departureTime":"09:57","routeNumber":"0","haltTime":"02:00","distance":"35.85","dayCount":"1","stnSerialNumber":"3"},{"stationCode":"CHLK","stationName":"CHAVALKHEDE","arrivalTime":"10:06","departureTime":"10:08","routeNumber":"0","haltTime":"02:00","distance":"47.34","dayCount":"1","stnSerialNumber":"4"},{"stationCode":"DXG","stationName":"DHARANGAON","arrivalTime":"10:14","departureTime":"10:16","routeNumber":"0","haltTime":"02:00","distance":"54.59","dayCount":"1","stnSerialNumber":"5"},{"stationCode":"BHNE","stationName":"BHONE","arrivalTime":"10:24","departureTime":"10:25","routeNumber":"0","haltTime":"01:00","distance":"61.39","dayCount":"1","stnSerialNumber":"6"},{"stationCode":"TKHE","stationName":"TAKARKHEDE","arrivalTime":"10:37","departureTime":"10:39","routeNumber":"0","haltTime":"02:00","distance":"68.02","dayCount":"1","stnSerialNumber":"7"},{"stationCode":"AN","stationName":"AMALNER","arrivalTime":"10:50","departureTime":"10:52","routeNumber":"0","haltTime":"02:00","distance":"79.54","dayCount":"1","stnSerialNumber":"8"},{"stationCode":"BRTK","stationName":"BHORTEX","arrivalTime":"11:01","departureTime":"11:03","routeNumber":"0","haltTime":"02:00","distance":"87.16","dayCount":"1","stnSerialNumber":"9"},{"stationCode":"PDP","stationName":"PADSE","arrivalTime":"11:10","departureTime":"11:12","routeNumber":"0","haltTime":"02:00","distance":"95.32","dayCount":"1","stnSerialNumber":"10"},{"stationCode":"BEW","stationName":"BETAVAD","arrivalTime":"11:19","departureTime":"11:20","routeNumber":"0","haltTime":"01:00","distance":"100.9","dayCount":"1","stnSerialNumber":"11"},{"stationCode":"NDN","stationName":"NARDANA","arrivalTime":"11:28","departureTime":"11:30","routeNumber":"0","haltTime":"02:00","distance":"107.71","dayCount":"1","stnSerialNumber":"12"},{"stationCode":"HOL","stationName":"HOL","arrivalTime":"11:37","departureTime":"11:38","routeNumber":"0","haltTime":"01:00","distance":"113.14","dayCount":"1","stnSerialNumber":"13"},{"stationCode":"SNK","stationName":"SINDKHEDA","arrivalTime":"11:50","departureTime":"11:52","routeNumber":"0","haltTime":"02:00","distance":"120.93","dayCount":"1","stnSerialNumber":"14"},{"stationCode":"SNSL","stationName":"SONSHELU","arrivalTime":"12:00","departureTime":"12:01","routeNumber":"0","haltTime":"01:00","distance":"126.79","dayCount":"1","stnSerialNumber":"15"},{"stationCode":"VKH","stationName":"VIKHRAN ROAD","arrivalTime":"12:10","departureTime":"12:12","routeNumber":"0","haltTime":"02:00","distance":"132.21","dayCount":"1","stnSerialNumber":"16"},{"stationCode":"DDE","stationName":"DONDAICHA","arrivalTime":"12:19","departureTime":"12:21","routeNumber":"0","haltTime":"02:00","distance":"140.37","dayCount":"1","stnSerialNumber":"17"},{"stationCode":"RNL","stationName":"RANALA","arrivalTime":"12:33","departureTime":"12:35","routeNumber":"0","haltTime":"02:00","distance":"152.35","dayCount":"1","stnSerialNumber":"18"},{"stationCode":"TISI","stationName":"TISI","arrivalTime":"12:54","departureTime":"12:56","routeNumber":"0","haltTime":"02:00","distance":"161.83","dayCount":"1","stnSerialNumber":"19"},{"stationCode":"CUE","stationName":"CHOUPALE","arrivalTime":"13:12","departureTime":"13:13","routeNumber":"0","haltTime":"01:00","distance":"170.0","dayCount":"1","stnSerialNumber":"20"},{"stationCode":"NDB","stationName":"NANDURBAR","arrivalTime":"13:40","departureTime":"00:00","routeNumber":"0","haltTime":"--","distance":"174.75","dayCount":"1","stnSerialNumber":"21"}],"generatedTimeStamp":{"year":2025,"month":2,"day":3,"hour":11,"minute":42,"second":33}}
